tdcrpy/TDCRPy.py
tdcrpy/TDCRPy1.py
tdcrpy/TDCR_model_lib.py
tdcrpy/TDCRoptimize.py
tdcrpy/__init__.py
tdcrpy/config.toml
tdcrpy/configDefault.toml
tdcrpy/test2.py
tdcrpy/test_randomGen.py
tdcrpy/MCNP-MATRIX/Spectra_for_analytical_model/dep_spectrum_C-14.txt
tdcrpy/MCNP-MATRIX/Spectra_for_analytical_model/dep_spectrum_Ca-45.txt
tdcrpy/MCNP-MATRIX/Spectra_for_analytical_model/dep_spectrum_Co-60.txt
tdcrpy/MCNP-MATRIX/Spectra_for_analytical_model/dep_spectrum_H-3.txt
tdcrpy/MCNP-MATRIX/Spectra_for_analytical_model/dep_spectrum_Ni-63.txt
tdcrpy/MCNP-MATRIX/Spectra_for_analytical_model/dep_spectrum_Pm-147.txt
tdcrpy/MCNP-MATRIX/Spectra_for_analytical_model/dep_spectrum_Pu-241.txt
tdcrpy/MCNP-MATRIX/Spectra_for_analytical_model/dep_spectrum_S-35.txt
tdcrpy/MCNP-MATRIX/Spectra_for_analytical_model/dep_spectrum_Sr-89.txt
tdcrpy/MCNP-MATRIX/Spectra_for_analytical_model/dep_spectrum_Sr-90.txt
tdcrpy/MCNP-MATRIX/Spectra_for_analytical_model/dep_spectrum_Tc-99.txt
tdcrpy/MCNP-MATRIX/matrice/fichier/E_depose.txt
tdcrpy/MCNP-MATRIX/matrice/fichier/matrice_10ml-beta-_1_200k.txt
tdcrpy/MCNP-MATRIX/matrice/fichier/matrice_10ml-beta-_2000_10000k.txt
tdcrpy/MCNP-MATRIX/matrice/fichier/matrice_10ml-beta-_200_2000k.txt
tdcrpy/MCNP-MATRIX/matrice/fichier/matrice_10ml-photon_1_200k.txt
tdcrpy/MCNP-MATRIX/matrice/fichier/matrice_10ml-photon_2000_10000k.txt
tdcrpy/MCNP-MATRIX/matrice/fichier/matrice_10ml-photon_200_2000k.txt
tdcrpy/MCNP-MATRIX/matrice/fichier/matrice_13ml-beta-_1_200k.txt
tdcrpy/MCNP-MATRIX/matrice/fichier/matrice_13ml-beta-_2000_10000k.txt
tdcrpy/MCNP-MATRIX/matrice/fichier/matrice_13ml-beta-_200_2000k.txt
tdcrpy/MCNP-MATRIX/matrice/fichier/matrice_13ml-photon_1_200k.txt
tdcrpy/MCNP-MATRIX/matrice/fichier/matrice_13ml-photon_2000_10000k.txt
tdcrpy/MCNP-MATRIX/matrice/fichier/matrice_13ml-photon_200_2000k.txt
tdcrpy/MCNP-MATRIX/matrice/fichier/matrice_16ml-beta-_1_200k.txt
tdcrpy/MCNP-MATRIX/matrice/fichier/matrice_16ml-beta-_2000_10000k.txt
tdcrpy-2.16.17.dist-info/licenses/LICENCE.md
tdcrpy-2.16.17.dist-info/METADATA
tdcrpy-2.16.17.dist-info/WHEEL
tdcrpy-2.16.17.dist-info/top_level.txt
tdcrpy-2.16.17.dist-info/RECORD
