Metadata-Version: 2.4
Name: TDCRPy
Version: 2.16.17
Summary: TDCR model
Home-page: https://pypi.org/project/TDCRPy/
Author: RomainCoulon (Romain Coulon)
Author-email: <romain.coulon@bipm.org>
Project-URL: Documentation, https://github.com/RomainCoulon/TDCRPy/
Keywords: Python,TDCR,Monte-Carlo,radionuclide,scintillation,counting
Classifier: Development Status :: 5 - Production/Stable
Classifier: Intended Audience :: Science/Research
Classifier: License :: OSI Approved :: MIT License
Classifier: Natural Language :: English
Classifier: Natural Language :: French
Classifier: Programming Language :: Python :: 3
Classifier: Operating System :: Unix
Classifier: Operating System :: MacOS :: MacOS X
Classifier: Operating System :: Microsoft :: Windows
Classifier: Topic :: Scientific/Engineering :: Physics
Requires-Python: >=3.11
License-File: LICENCE.md
Requires-Dist: numpy
Requires-Dist: tqdm
Requires-Dist: setuptools
Requires-Dist: scipy
Requires-Dist: configparser
Requires-Dist: importlib.resources
Requires-Dist: matplotlib
Dynamic: author
Dynamic: author-email
Dynamic: classifier
Dynamic: description
Dynamic: description-content-type
Dynamic: home-page
Dynamic: keywords
Dynamic: license-file
Dynamic: project-url
Dynamic: requires-dist
Dynamic: requires-python
Dynamic: summary
